financecalculator2025/__init__.py
financecalculator2025/contribution.py
financecalculator2025/future_value.py
financecalculator2025/n_periods.py
financecalculator2025/present_value.py
financecalculator2025-0.2.2.dist-info/LICENSE
financecalculator2025-0.2.2.dist-info/METADATA
financecalculator2025-0.2.2.dist-info/WHEEL
financecalculator2025-0.2.2.dist-info/RECORD
