Metadata-Version: 2.3
Name: financecalculator2025
Version: 0.2.2
Summary: A package for calculating Financial Services specifically for loans or investment scenarios.
License: MIT
Author: Meagan Gardner
Requires-Python: >=3.11,<4.0
Classifier: License :: OSI Approved :: MIT License
Classifier: Programming Language :: Python :: 3
Classifier: Programming Language :: Python :: 3.11
Classifier: Programming Language :: Python :: 3.12
Classifier: Programming Language :: Python :: 3.13
Requires-Dist: pandas (>=2.2.3,<3.0.0)
